pyphotonics/VERSION
pyphotonics/__init__.py
pyphotonics/__main__.py
pyphotonics/cli.py
pyphotonics/constants.py
pyphotonics/photoluminescence.py
pyphotonics/version.py
pyphotonics-0.2.0.dist-info/LICENSE.txt
pyphotonics-0.2.0.dist-info/METADATA
pyphotonics-0.2.0.dist-info/WHEEL
pyphotonics-0.2.0.dist-info/entry_points.txt
pyphotonics-0.2.0.dist-info/top_level.txt
pyphotonics-0.2.0.dist-info/RECORD
