Metadata-Version: 2.1
Name: pyphotonics
Version: 0.2.0
Summary: The PyPhotonics python code is a post-processing code written entirely in python which takes as input the output files of the VASP and phonopy codes for a defect system, and calculates the Huang-Rhys factor and the PL lineshapes for that system.
Home-page: https://github.com/sheriftawfikabbas/pyphotonics
Author: Sherif Abdulkader Tawfik
Author-email: sherif.tawfic@gmail.com
License: gpl-3.0
Keywords: DFT,Material science,Photoluminescence,VASP
License-File: LICENSE.txt
Requires-Dist: scipy
Requires-Dist: numpy
Requires-Dist: pandas
Requires-Dist: matplotlib
Requires-Dist: pymatgen
Requires-Dist: oganesson
